nodeconductor_zabbix/__init__.py
nodeconductor_zabbix/admin.py
nodeconductor_zabbix/apps.py
nodeconductor_zabbix/backend.py
nodeconductor_zabbix/executors.py
nodeconductor_zabbix/extension.py
nodeconductor_zabbix/filters.py
nodeconductor_zabbix/handlers.py
nodeconductor_zabbix/managers.py
nodeconductor_zabbix/models.py
nodeconductor_zabbix/perms.py
nodeconductor_zabbix/serializers.py
nodeconductor_zabbix/tasks.py
nodeconductor_zabbix/urls.py
nodeconductor_zabbix/utils.py
nodeconductor_zabbix/views.py
nodeconductor_zabbix/migrations/0001_squashed_0007_add_sla.py
nodeconductor_zabbix/migrations/0008_add_itservice_trigger.py
nodeconductor_zabbix/migrations/0009_itservices_as_resource.py
nodeconductor_zabbix/migrations/0010_remove_spl_state.py
nodeconductor_zabbix/migrations/0011_migrate_state_field.py
nodeconductor_zabbix/migrations/0012_users_and_groups.py
nodeconductor_zabbix/migrations/0013_host_status_and_error.py
nodeconductor_zabbix/migrations/0014_add_key_to_item.py
nodeconductor_zabbix/migrations/0015_template_parents.py
nodeconductor_zabbix/migrations/__init__.py
nodeconductor_zabbix-0.6.0.dist-info/DESCRIPTION.rst
nodeconductor_zabbix-0.6.0.dist-info/METADATA
nodeconductor_zabbix-0.6.0.dist-info/RECORD
nodeconductor_zabbix-0.6.0.dist-info/WHEEL
nodeconductor_zabbix-0.6.0.dist-info/entry_points.txt
nodeconductor_zabbix-0.6.0.dist-info/metadata.json
nodeconductor_zabbix-0.6.0.dist-info/top_level.txt
