Metadata-Version: 2.0
Name: nodeconductor-zabbix
Version: 0.6.0
Summary: NodeConductor Zabbix adds support for Zabbix monitoring server management
Home-page: http://nodeconductor.com
Author: OpenNode Team
Author-email: info@opennodecloud.com
License: UNKNOWN
Platform: UNKNOWN
Classifier: Framework :: Django
Classifier: Intended Audience :: Developers
Classifier: Intended Audience :: System Administrators
Classifier: Operating System :: OS Independent
Classifier: License :: OSI Approved :: MIT License
Requires-Dist: nodeconductor (>=0.107.0)
Requires-Dist: pyzabbix (>=0.7.2)
Provides-Extra: dev
Requires-Dist: Sphinx (==1.2.2); extra == 'dev'
